cffex/__init__ .py
cffex/commonfuns.py
cffex/gbfutures.py
cffex/indexfutures.py
cffex/indexoptions.py
pycffex-0.3.2.dist-info/licenses/LICENSE
pycffex-0.3.2.dist-info/METADATA
pycffex-0.3.2.dist-info/WHEEL
pycffex-0.3.2.dist-info/top_level.txt
pycffex-0.3.2.dist-info/RECORD
