Metadata-Version: 2.4
Name: pycffex
Version: 0.3.2
Summary: cffex with python: gb futures, index futures, and options
Author-email: rhozhang <rhozhang@163.com>
License-Expression: MIT
Project-URL: Homepage, https://github.com/rhozhang/pycffex
Project-URL: Issues, https://github.com/rhozhang/pycffex/issues
Classifier: Programming Language :: Python :: 3
Classifier: Operating System :: OS Independent
Requires-Python: >=3.12
License-File: LICENSE
Requires-Dist: numpy
Requires-Dist: scipy
Requires-Dist: pandas
Requires-Dist: polars
Requires-Dist: akshare
Requires-Dist: cnexchcal
Requires-Dist: cnfixedratebond
Dynamic: license-file
